pdnssoccli/__init__.py
pdnssoccli/pdnssoccli.py
pdnssoccli/subcommands/__init__.py
pdnssoccli/subcommands/alert.py
pdnssoccli/subcommands/correlate.py
pdnssoccli/subcommands/daemonize.py
pdnssoccli/subcommands/fetch_iocs.py
pdnssoccli/subcommands/utils.py
pdnssoccli/utils/__init__.py
pdnssoccli/utils/alert.py
pdnssoccli/utils/correlation.py
pdnssoccli/utils/enrichment.py
pdnssoccli/utils/file.py
pdnssoccli/utils/time.py
resources/alert_email_template.html
pdnssoc_cli-0.0.5.dist-info/LICENSE.txt
pdnssoc_cli-0.0.5.dist-info/METADATA
pdnssoc_cli-0.0.5.dist-info/WHEEL
pdnssoc_cli-0.0.5.dist-info/entry_points.txt
pdnssoc_cli-0.0.5.dist-info/top_level.txt
pdnssoc_cli-0.0.5.dist-info/RECORD
