Metadata-Version: 2.1
Name: pdnssoc-cli
Version: 0.0.5
Summary: Correlate dnstap files with MISP
Home-page: https://github.com/CERN-CERT/pdnssoc-cli
Author: CERN Computer Security Team
Author-email: computer.security@cern.ch
License: MIT
Project-URL: Documentation, https://github.com/CERN-CERT/pdnssoc-cli
Platform: any
Classifier: Development Status :: 4 - Beta
Classifier: Programming Language :: Python
License-File: LICENSE.txt
Requires-Dist: click
Requires-Dist: jsonlines
Requires-Dist: cachetools
Requires-Dist: pymisp
Requires-Dist: pyyaml
Requires-Dist: aiofiles
Requires-Dist: ipaddress
Requires-Dist: schedule
Requires-Dist: pytz
Requires-Dist: jinja2
Requires-Dist: importlib-metadata ; python_version < "3.8"
Provides-Extra: testing
Requires-Dist: setuptools ; extra == 'testing'
Requires-Dist: pytest ; extra == 'testing'
